LICENCE
README.md
setup.py
hair_color_detector/79999_iter.pth
hair_color_detector/HairColorDetector.py
hair_color_detector/HairSegmentator.py
hair_color_detector/__init__.py
hair_color_detector/model.py
hair_color_detector/resnet.py
hair_color_detector.egg-info/PKG-INFO
hair_color_detector.egg-info/SOURCES.txt
hair_color_detector.egg-info/dependency_links.txt
hair_color_detector.egg-info/requires.txt
hair_color_detector.egg-info/top_level.txt